progplot/__init__.py
progplot/accident.jpg
progplot/error.png
progplot/functions.py
progplot/investigate.png
progplot/medical.jpg
progplot/plotter.py
progplot/theft.jpg
progplot/__pycache__/__init__.cpython-37.pyc
progplot/__pycache__/functions.cpython-37.pyc
progplot/__pycache__/plotter.cpython-37.pyc
progplot-0.2.22.dist-info/METADATA
progplot-0.2.22.dist-info/WHEEL
progplot-0.2.22.dist-info/top_level.txt
progplot-0.2.22.dist-info/RECORD
