Metadata-Version: 2.1
Name: progplot
Version: 0.2.22
Summary: progplot - Timeseries barplot animations.
Home-page: https://github.com/lewis-morris/progplot
Author: Lewis Morris
Author-email: lewis.morris@gmail.com
License: MIT
Platform: UNKNOWN
Requires-Dist: pandas (>=1.0.3)
Requires-Dist: seaborn (>=0.10.1)
Requires-Dist: matplotlib (>=3.1.3)
Requires-Dist: Pillow (>=7.1.1)
Requires-Dist: numpy (>=1.18.1)
Requires-Dist: opencv-python (>=4.1)
